productstatus/__init__.py
productstatus/api.py
productstatus/cli.py
productstatus/event.py
productstatus/exceptions.py
productstatus/utils.py
productstatus_client-7.0.0.dist-info/LICENSE
productstatus_client-7.0.0.dist-info/METADATA
productstatus_client-7.0.0.dist-info/WHEEL
productstatus_client-7.0.0.dist-info/top_level.txt
productstatus_client-7.0.0.dist-info/RECORD
