Metadata-Version: 2.1
Name: productstatus-client
Version: 7.0.0
Summary: Productstatus REST API client
Home-page: https://github.com/metno/python-productstatus-client
Author: MET Norway
Author-email: UNKNOWN
License: UNKNOWN
Download-URL: https://github.com/metno/python-productstatus-client
Platform: UNKNOWN
Requires-Dist: nose (==1.3.7)
Requires-Dist: requests (==2.20.0)
Requires-Dist: python-dateutil (==2.7.5)
Requires-Dist: httmock (==1.2.6)
Requires-Dist: kafka-python (==1.4.3)
Requires-Dist: mock (==2.0.0)
